mrirage/__init__.py
mrirage/common/__init__.py
mrirage/common/common.py
mrirage/common/mpl_dom/__init__.py
mrirage/common/mpl_dom/mpl.py
mrirage/composition/__init__.py
mrirage/composition/composition.py
mrirage/composition/grid.py
mrirage/composition/layer/__init__.py
mrirage/composition/layer/annotation.py
mrirage/composition/layer/image_3d.py
mrirage/composition/layer/layer.py
mrirage/composition/layer/style_data.py
mrirage/composition/view/__init__.py
mrirage/composition/view/view.py
mrirage/datacube/__init__.py
mrirage/datacube/datacube.py
mrirage/loader/__init__.py
mrirage/loader/nifti.py
mrirage/slicer/__init__.py
mrirage/slicer/bounds.py
mrirage/slicer/common.py
mrirage/utils/__init__.py
mrirage/utils/composition.py
mrirage-0.1.1.dist-info/LICENSE
mrirage-0.1.1.dist-info/METADATA
mrirage-0.1.1.dist-info/WHEEL
mrirage-0.1.1.dist-info/RECORD
