Metadata-Version: 2.1
Name: mrirage
Version: 0.1.1
Summary: MRI visualization
Home-page: https://github.com/nx10/mrirage
License: MIT
Keywords: MRI,visualization
Author: Florian Rupprecht
Author-email: floruppr@gmail.com
Requires-Python: >=3.10,<3.13
Classifier: License :: OSI Approved :: MIT License
Classifier: Programming Language :: Python :: 3
Classifier: Programming Language :: Python :: 3.10
Classifier: Programming Language :: Python :: 3.11
Provides-Extra: docs
Requires-Dist: fineslice (>=0.0.2,<0.0.3)
Requires-Dist: matplotlib (>=3.8.0,<4.0.0)
Requires-Dist: nibabel (>=5.1.0,<6.0.0)
Requires-Dist: numpy (>=1.26.1,<2.0.0)
Requires-Dist: scipy (>=1.11.3,<2.0.0)
Project-URL: Documentation, https://github.com/nx10/mrirage/docs
Project-URL: Repository, https://github.com/nx10/mrirage
